environmentfinder/App.ipynb
environmentfinder/__init__.py
environmentfinder/environmentfinder.py
environmentfinder/logo-notext.png
environmentfinder/logo.png
environmentfinder/examples/Ga_II.vasp
environmentfinder/examples/IceIh.pdb
environmentfinder/examples/urea2.pdb
environmentfinder-1.1.6.data/scripts/environmentfinder
environmentfinder-1.1.6.dist-info/LICENSE
environmentfinder-1.1.6.dist-info/METADATA
environmentfinder-1.1.6.dist-info/WHEEL
environmentfinder-1.1.6.dist-info/top_level.txt
environmentfinder-1.1.6.dist-info/RECORD
