Metadata-Version: 2.1
Name: environmentfinder
Version: 1.1.6
Summary: Tool for finding atomic environments in crystal structures
Home-page: http://github.com/PabloPiaggi/EnvironmentFinder
Author: Pablo Piaggi
Author-email: ppiaggi@princeton.edu
License: GNU General Public License v3.0
License-File: LICENSE
Requires-Dist: numpy ==1.24.2
Requires-Dist: ase ==3.22.1
Requires-Dist: ipywidgets ==8.1.3
Requires-Dist: voila ==0.5.7
Requires-Dist: tqdm ==4.66.4
Requires-Dist: nglview ==3.1.2
Requires-Dist: markdown ==3.6
